README.txt
setup.py
django_testrecorder.egg-info/PKG-INFO
django_testrecorder.egg-info/SOURCES.txt
django_testrecorder.egg-info/dependency_links.txt
django_testrecorder.egg-info/not-zip-safe
django_testrecorder.egg-info/top_level.txt
testrecorder/__init__.py
testrecorder/middleware.py
testrecorder/models.py
testrecorder/settings.py
testrecorder/toolbar.py
testrecorder/urls.py
testrecorder/utils.py
testrecorder/views.py
testrecorder/management/__init__.py
testrecorder/management/commands/__init__.py
testrecorder/management/commands/recorderserver.py
testrecorder/panels/__init__.py
testrecorder/panels/assertion.py
testrecorder/panels/classname.py
testrecorder/panels/code.py
testrecorder/panels/fixture.py
testrecorder/panels/functionname.py
testrecorder/panels/record.py
testrecorder/templatetags/__init__.py
testrecorder/templatetags/code_tags.py