Metadata-Version: 1.0
Name: django-testrecorder
Version: 0.1
Summary: Tool for generating tests for Django projects.
Home-page: https://github.com/pydevua/django-testrecorder
Author: UNKNOWN
Author-email: UNKNOWN
License: UNKNOWN
Platform: UNKNOWN
